zexcel/__init__.py
zexcel/chart.py
zexcel/mock.py
zexcel/numeric.py
zexcel/table/__init__.py
zexcel/table/column.py
zexcel/table/element.py
zexcel-0.1.0.dist-info/METADATA
zexcel-0.1.0.dist-info/WHEEL
zexcel-0.1.0.dist-info/licenses/LICENSE
zexcel-0.1.0.dist-info/RECORD
