Metadata-Version: 2.1
Name: zexcel
Version: 0.1.0
Summary: zen excel library
Project-URL: Homepage, https://github.com/inspirare6/zexcel
Project-URL: Bug Tracker, https://github.com/inspirare6/zexcel/issues
Author-email: inspirare6 <inspirare6@163.com>
License-File: LICENSE
Classifier: License :: OSI Approved :: MIT License
Classifier: Operating System :: OS Independent
Classifier: Programming Language :: Python :: 3
Requires-Python: >=3.7
Requires-Dist: matplotlib
Requires-Dist: numpy
Requires-Dist: openpyxl
Requires-Dist: pandas==1.0.1
